ganok/Device.py
ganok/WebAdress.py
ganok/__init__.py
ganok/clines_ph_web.py
ganok/copyright.py
ganok/encoder.py
ganok/mb.py
ganok/send_server.py
ganok-1.1.0.dist-info/LICENCE
ganok-1.1.0.dist-info/METADATA
ganok-1.1.0.dist-info/WHEEL
ganok-1.1.0.dist-info/top_level.txt
ganok-1.1.0.dist-info/RECORD
